starcoin/__init__.py
starcoin/bcs/__init__.py
starcoin/sdk/__init__.py
starcoin/sdk/auth_key.py
starcoin/sdk/bech32.py
starcoin/sdk/client.py
starcoin/sdk/local_account.py
starcoin/sdk/receipt_identifier.py
starcoin/sdk/utils.py
starcoin/serde_binary/__init__.py
starcoin/serde_types/__init__.py
starcoin/starcoin_stdlib/__init__.py
starcoin/starcoin_types/__init__.py
tests/__init__.py
tests/test_jsonrpc.py
tests/test_receipt_identifier.py
tests/test_verify_signed_message.py
starcoin_sdk_python-1.4.1.dist-info/METADATA
starcoin_sdk_python-1.4.1.dist-info/WHEEL
starcoin_sdk_python-1.4.1.dist-info/top_level.txt
starcoin_sdk_python-1.4.1.dist-info/zip-safe
starcoin_sdk_python-1.4.1.dist-info/RECORD
