Metadata-Version: 2.1
Name: starcoin-sdk-python
Version: 1.4.1
Summary: The Python Client SDK for Starcoin
Home-page: https://github.com/fikgol/starcoin-sdk-python
License: Apache-2.0
Platform: UNKNOWN
Requires-Python: >=3.7
Requires-Dist: requests (>=2.20.0)
Requires-Dist: cryptography (>=2.8)
Requires-Dist: numpy (>=1.18)
